openremote_cli/cli.py
openremote_cli/config.py
openremote_cli/email.py
openremote_cli/gen_aws_smtp_credentials.py
openremote_cli/scripts.py
openremote_cli/shell.py
openremote_cli/testplan.py
openremote_cli-0.6.65.dist-info/LICENSE.txt
openremote_cli-0.6.65.dist-info/METADATA
openremote_cli-0.6.65.dist-info/entry_points.txt
openremote_cli-0.6.65.dist-info/WHEEL
openremote_cli-0.6.65.dist-info/RECORD
