Metadata-Version: 2.1
Name: openremote-cli
Version: 0.6.65
Summary: OpenRemote Command-line interface
Home-page: https://www.openremote.io
License: AGPLv3
Keywords: openremote,iot,cli
Author: Michal Rutka
Author-email: michal@openremote.io
Maintainer: OpenRemote
Maintainer-email: developers@openremote.io
Requires-Python: >=3.9,<4.0
Classifier: License :: Other/Proprietary License
Classifier: Programming Language :: Python :: 3
Classifier: Programming Language :: Python :: 3.9
Classifier: Programming Language :: Python :: 3.10
Classifier: Programming Language :: Python :: 3.11
Requires-Dist: emojis (>=0.6.0,<0.7.0)
Requires-Dist: oronium (>=1.0.11,<2.0.0)
Requires-Dist: python-keycloak (>=0.24.0,<0.25.0)
Requires-Dist: requests (>=2.25.1,<3.0.0)
Requires-Dist: urllib3 (>=1.26.14)
Requires-Dist: wget (>=3.2,<4.0)
Project-URL: Documentation, https://github.com/openremote/openremote/wiki
Project-URL: Repository, https://github.com/openremote/openremote
